das_readability/__init__.py
das_readability/__main__.py
das_readability/readability.py
das_readability-2.0.0.dist-info/LICENSE
das_readability-2.0.0.dist-info/METADATA
das_readability-2.0.0.dist-info/WHEEL
das_readability-2.0.0.dist-info/entry_points.txt
das_readability-2.0.0.dist-info/RECORD
